florodoro/__init__.py
florodoro/history.py
florodoro/plants.py
florodoro/utilities.py
florodoro/version.py
florodoro/widgets.py
florodoro/images/icon.svg
florodoro/images/logo.svg
florodoro/images/preview.svg
florodoro/sounds/break_done.wav
florodoro/sounds/study_done.wav
florodoro-0.8.data/data/CHANGELOG.md
florodoro-0.8.data/data/LICENSE
florodoro-0.8.data/data/README.md
florodoro-0.8.data/data/requirements.txt
florodoro-0.8.dist-info/LICENSE
florodoro-0.8.dist-info/METADATA
florodoro-0.8.dist-info/WHEEL
florodoro-0.8.dist-info/entry_points.txt
florodoro-0.8.dist-info/top_level.txt
florodoro-0.8.dist-info/RECORD
