Metadata-Version: 2.1
Name: florodoro
Version: 0.8
Summary: A pomodoro timer that grows procedurally generated trees and flowers while you're studying.
Home-page: https://github.com/xiaoxiae/Florodoro
Author: Tomáš Sláma
Author-email: tomas@slama.dev
Keywords: education pyqt5 plants pomodoro
Classifier: Programming Language :: Python :: 3
Classifier: License :: OSI Approved :: GNU General Public License v3 (GPLv3)
Classifier: Operating System :: OS Independent
Requires-Python: >=3.7.1
License-File: LICENSE
Requires-Dist: pyqt5
Requires-Dist: pyqtchart
Requires-Dist: plyer
Requires-Dist: qtawesome
Requires-Dist: PyYAML
